clipboard_processor/__init__.py
clipboard_processor/_version.py
clipboard_processor/cli.py
clipboard_processor/input/__init__.py
clipboard_processor/input/_base.py
clipboard_processor/input/pyperclip.py
clipboard_processor/input/xclip.py
clipboard_processor/output/__init__.py
clipboard_processor/output/_base.py
clipboard_processor/output/notify.py
clipboard_processor/output/stdout.py
clipboard_processor/output/ui.py
clipboard_processor/plugins/__init__.py
clipboard_processor/plugins/_base.py
clipboard_processor/plugins/aws_account_id.py
clipboard_processor/plugins/base64.py
clipboard_processor/plugins/cron.py
clipboard_processor/plugins/hex.py
clipboard_processor/plugins/jwt.py
clipboard_processor/plugins/oui.py
clipboard_processor/plugins/ulid.py
clipboard_processor/plugins/unixtime.py
clipboard_processor/plugins/vin.py
clipboard_processor/plugins/well_known.py
clipboard_processor-0.3.1.dist-info/METADATA
clipboard_processor-0.3.1.dist-info/WHEEL
clipboard_processor-0.3.1.dist-info/entry_points.txt
clipboard_processor-0.3.1.dist-info/licenses/LICENSE
clipboard_processor-0.3.1.dist-info/RECORD
