Metadata-Version: 2.4
Name: clipboard-processor
Version: 0.3.1
Summary: Process clipboard content and show helpful overlays or notifications based on the content, e.g. parse UNIX timestamps, AWS account IDs, VINs, base64 strings and more.
Project-URL: Homepage, https://github.com/tom-mi/clipboard-processor
Project-URL: Repository, https://github.com/tom-mi/clipboard-processor.git
Project-URL: Issues, https://github.com/tom-mi/clipboard-processor/issues
Author-email: Thomas Reifenberger <tom-mi@users.noreply.github.com>
License-Expression: MIT
License-File: LICENSE
Classifier: Development Status :: 4 - Beta
Classifier: Programming Language :: Python
Classifier: Programming Language :: Python :: 3.9
Classifier: Programming Language :: Python :: 3.10
Classifier: Programming Language :: Python :: 3.11
Classifier: Programming Language :: Python :: 3.12
Classifier: Programming Language :: Python :: 3.13
Requires-Python: >=3.9
Requires-Dist: pyperclip>=1.9.0
Provides-Extra: all
Requires-Dist: cron-descriptor; extra == 'all'
Requires-Dist: desktop-notifier; extra == 'all'
Requires-Dist: netaddr; extra == 'all'
Requires-Dist: pyjwt[crypto]; extra == 'all'
Requires-Dist: python-ulid; extra == 'all'
Requires-Dist: vininfo; extra == 'all'
Provides-Extra: cron
Requires-Dist: cron-descriptor; extra == 'cron'
Provides-Extra: jwt
Requires-Dist: pyjwt[crypto]; extra == 'jwt'
Provides-Extra: notify
Requires-Dist: desktop-notifier; extra == 'notify'
Provides-Extra: oui
Requires-Dist: netaddr; extra == 'oui'
Provides-Extra: ulid
Requires-Dist: python-ulid; extra == 'ulid'
Provides-Extra: vin
Requires-Dist: vininfo; extra == 'vin'
